sensory_data_client/__init__.py
sensory_data_client/cli.py
sensory_data_client/client.py
sensory_data_client/config.py
sensory_data_client/exceptions.py
sensory_data_client/logging.py
sensory_data_client/db/__init__.py
sensory_data_client/db/base.py
sensory_data_client/db/triggers.py
sensory_data_client/db/uow.py
sensory_data_client/db/auth/refresh_token_orm.py
sensory_data_client/db/billing/payment_orm.py
sensory_data_client/db/billing/plan_orm.py
sensory_data_client/db/billing/subscription_orm.py
sensory_data_client/db/documents/doc_bullet_orm.py
sensory_data_client/db/documents/document_orm.py
sensory_data_client/db/documents/document_permissions.py
sensory_data_client/db/documents/storage_orm.py
sensory_data_client/db/documents/lines/audioLine_orm.py
sensory_data_client/db/documents/lines/documentLine_orm.py
sensory_data_client/db/documents/lines/imageLine_orm.py
sensory_data_client/db/documents/lines/rawline_orm.py
sensory_data_client/db/tags/autotag_task_orm.py
sensory_data_client/db/tags/document_tag_orm.py
sensory_data_client/db/tags/tag_orm.py
sensory_data_client/db/users/groups.py
sensory_data_client/db/users/user_group_membership.py
sensory_data_client/db/users/users.py
sensory_data_client/models/__init__.py
sensory_data_client/models/audio.py
sensory_data_client/models/document.py
sensory_data_client/models/group.py
sensory_data_client/models/line.py
sensory_data_client/repositories/__init__.py
sensory_data_client/repositories/es_repository.py
sensory_data_client/repositories/minio_repository.py
sensory_data_client/repositories/pg_repositoryBullets.py
sensory_data_client/repositories/pg_repositoryMeta.py
sensory_data_client/repositories/pg_repositoryObj.py
sensory_data_client/repositories/auth/pg_repositoryAuth.py
sensory_data_client/repositories/auth/pg_repositoryBilling.py
sensory_data_client/repositories/auth/pg_repositoryGroup.py
sensory_data_client/repositories/auth/pg_repositoryPermission.py
sensory_data_client-0.2.44.dist-info/METADATA
sensory_data_client-0.2.44.dist-info/WHEEL
sensory_data_client-0.2.44.dist-info/entry_points.txt
sensory_data_client-0.2.44.dist-info/top_level.txt
sensory_data_client-0.2.44.dist-info/RECORD
