Metadata-Version: 2.4
Name: sensory-data-client
Version: 0.2.44
Summary: Asynchronous facade for PostgreSQL and MinIO for corporate semantic search systems.
Author-email: Fox <fox@sensorylab.ru>
License: MIT
Classifier: Programming Language :: Python :: 3
Classifier: Programming Language :: Python :: 3.10
Classifier: Programming Language :: Python :: 3.11
Classifier: License :: OSI Approved :: MIT License
Classifier: Operating System :: OS Independent
Classifier: Intended Audience :: Developers
Classifier: Topic :: Database
Classifier: Topic :: Software Development :: Libraries :: Python Modules
Requires-Python: >=3.10
Requires-Dist: elasticsearch
Requires-Dist: pgvector
Requires-Dist: passlib
Requires-Dist: sqlalchemy[asyncio]
Requires-Dist: asyncpg
Requires-Dist: minio
Requires-Dist: pydantic
Requires-Dist: pydantic-settings
Requires-Dist: alembic
Requires-Dist: typer
Requires-Dist: importlib-resources; python_version < "3.9"
Provides-Extra: dev
Requires-Dist: pytest; extra == "dev"
Requires-Dist: pytest-asyncio; extra == "dev"
Requires-Dist: pytest-cov; extra == "dev"
Requires-Dist: testcontainers; extra == "dev"
Requires-Dist: faker; extra == "dev"
Requires-Dist: black; extra == "dev"
Requires-Dist: isort; extra == "dev"
Requires-Dist: mypy; extra == "dev"
Requires-Dist: python-dotenv; extra == "dev"
